axtoolkit/__init__.py
axtoolkit/base_tools/__init__.py
axtoolkit/base_tools/color_tools.py
axtoolkit/base_tools/fig_tools.py
axtoolkit/base_tools/file_tools.py
axtoolkit/base_tools/ligand_tools.py
axtoolkit/base_tools/multi_run_for_tools.py
axtoolkit/base_tools/py_decoration.py
axtoolkit/base_tools/seq_tools.py
axtoolkit/base_tools/sh_tools.py
axtoolkit/base_tools/text_tools.py
axtoolkit-0.1.2.dist-info/LICENSE
axtoolkit-0.1.2.dist-info/METADATA
axtoolkit-0.1.2.dist-info/WHEEL
axtoolkit-0.1.2.dist-info/entry_points.txt
axtoolkit-0.1.2.dist-info/top_level.txt
axtoolkit-0.1.2.dist-info/RECORD
